lab4_8_rtl.v
// ============================================================
// Lab 4-8 : FIFO
// Objective: Using the RAM structure, construct a FIFO with
// 128 entries, each 8 bits wide.
//   d_in_valid : push d_in into the FIFO (ignored when full)
//   d_out_req  : pop the oldest entry to d_out (ignored when empty)
//   full/empty : status flags
// ============================================================
`timescale 1ns/1ps

module fifo(d_in, d_in_valid, d_out, d_out_req, clk, full, empty);
    input  [7:0] d_in;
    input        d_in_valid, d_out_req, clk;
    output reg [7:0] d_out;
    output       full, empty;

    reg [7:0] mem [0:127];   // 128 entries x 8 bits
    reg [6:0] wr_ptr, rd_ptr;
    reg [7:0] count;         // 0..128

    integer i;
    initial begin
        wr_ptr = 7'd0; rd_ptr = 7'd0; count = 8'd0; d_out = 8'd0;
        for (i = 0; i < 128; i = i + 1) mem[i] = 8'd0;
    end

    assign full  = (count == 8'd128);
    assign empty = (count == 8'd0);

    wire do_push = d_in_valid & ~full;
    wire do_pop  = d_out_req  & ~empty;

    always @(posedge clk) begin
        if (do_push) begin
            mem[wr_ptr] <= d_in;
            wr_ptr      <= wr_ptr + 7'd1;
        end
        if (do_pop) begin
            d_out  <= mem[rd_ptr];
            rd_ptr <= rd_ptr + 7'd1;
        end
        case ({do_push, do_pop})
            2'b10:   count <= count + 8'd1;
            2'b01:   count <= count - 8'd1;
            default: count <= count;
        endcase
    end
endmodule

lab4_8_tb.v
// ============================================================
// Lab 4-8 : Testbench
// push/pop checks, full flag, empty flag, and simultaneous
// push+pop while full.
// ============================================================
`timescale 1ns/1ps
module lab4_8_tb;
    reg clk = 0;
    always #5 clk = ~clk;

    integer errors = 0;
    integer i;

    reg  [7:0] d_in;
    reg        d_in_valid, d_out_req;
    wire [7:0] d_out;
    wire       full, empty;
    fifo dut (.d_in(d_in), .d_in_valid(d_in_valid), .d_out(d_out),
              .d_out_req(d_out_req), .clk(clk), .full(full), .empty(empty));

    task check;
        input condition;
      input [2255:0] msg;
        begin
            if (!condition) begin
                errors = errors + 1;
                $display("FAIL: %0s (time=%0t)", msg, $time);
            end
          else $display("PASS: %0s (time=%0t)", msg, $time);
        end
    endtask

    task push;
        input [7:0] v;
        begin
            d_in = v; d_in_valid = 1'b1;
            @(posedge clk); #1;
            d_in_valid = 1'b0;
        end
    endtask

    task pop_check;
        input [7:0] exp;
        input [255:0] msg;
        begin
            d_out_req = 1'b1;
            @(posedge clk); #1;
            d_out_req = 1'b0;
            check(d_out === exp, msg);
        end
    endtask

    initial begin
        d_in = 0; d_in_valid = 0; d_out_req = 0;

        // ---- empty at start ----
        #1; check(empty === 1'b1, "FIFO empty after reset");

        // ---- basic push / pop (FIFO order) ----
        push(8'h11); push(8'h22); push(8'h33);
        check(empty === 1'b0, "not empty after pushes");
        pop_check(8'h11, "pop 1st = 0x11");
        pop_check(8'h22, "pop 2nd = 0x22");
        pop_check(8'h33, "pop 3rd = 0x33");
        check(empty === 1'b1, "empty after draining");

        // ---- fill completely ----
        for (i = 0; i < 128; i = i + 1) push(i[7:0]);
        check(full === 1'b1, "full after 128 pushes");
        push(8'hEE);   // must be ignored
        check(full === 1'b1, "push ignored while full");

        // ---- simultaneous push + pop while full ----
        d_in = 8'hAA; d_in_valid = 1'b1; d_out_req = 1'b1;
        @(posedge clk); #1;
        d_in_valid = 1'b0; d_out_req = 1'b0;
        check(d_out === 8'd0,  "simultaneous pop returns oldest entry 0");
      check(full !== 1'b1,   "should not be full after simultaneous push+pop because push was ignored due to fifo full at that time and popped successful because it was not empty ");
      @(posedge clk); #1;
      @(posedge clk); #1;
      pop_check(8'd1, "pushed value comes out after the old entries");
        pop_check(8'd2,  "order preserved after simultaneous access");
      

        // ---- drain everything ----
        for (i = 3; i < 128; i = i + 1) begin
            d_out_req = 1'b1;
            @(posedge clk); #1;
            d_out_req = 1'b0;
            if (d_out !== (i[7:0])) begin
                errors = errors + 1;
                $display("FAIL: drain[%0d] = %02x exp=%02x", i, d_out, i[7:0]);
            end
          	else $display("PASS: drain[%0d] = %02x exp=%02x", i, d_out, i[7:0]);
        end
        check(empty === 1'b1, "empty after full drain");

        if (errors == 0) $display("LAB 4-8 PASSED");
        else             $display("LAB 4-8 FAILED (%0d errors)", errors);
        $finish;
    end
  initial begin
  	$dumpfile("dump.vcd"); // waveform file name
	$dumpvars; 
  end
endmodule

dump.vcd
$date
	Sun Sep 20 22:34:50 2026
$end
$version
	Icarus Verilog
$end
$timescale
	1ps
$end
$scope module lab4_8_tb $end
$var wire 1 ! full $end
$var wire 1 " empty $end
$var wire 8 # d_out [7:0] $end
$var reg 1 $ clk $end
$var reg 8 % d_in [7:0] $end
$var reg 1 & d_in_valid $end
$var reg 1 ' d_out_req $end
$var integer 32 ( errors [31:0] $end
$var integer 32 ) i [31:0] $end
$scope module dut $end
$var wire 1 $ clk $end
$var wire 8 * d_in [7:0] $end
$var wire 1 & d_in_valid $end
$var wire 1 ' d_out_req $end
$var wire 1 + do_pop $end
$var wire 1 , do_push $end
$var wire 1 ! full $end
$var wire 1 " empty $end
$var reg 8 - count [7:0] $end
$var reg 8 . d_out [7:0] $end
$var reg 7 / rd_ptr [6:0] $end
$var reg 7 0 wr_ptr [6:0] $end
$var integer 32 1 i [31:0] $end
$upscope $end
$scope task check $end
$var reg 1 2 condition $end
$var reg 2256 3 msg [2255:0] $end
$upscope $end
$scope task pop_check $end
$var reg 8 4 exp [7:0] $end
$var reg 256 5 msg [255:0] $end
$upscope $end
$scope task push $end
$var reg 8 6 v [7:0] $end
$upscope $end
$upscope $end
$enddefinitions $end
$comment Show the parameter values. $end
$dumpall
$end
#0
$dumpvars
bx 6
bx 5
bx 4
bx 3
x2
b10000000 1
b0 0
b0 /
b0 .
b0 -
0,
0+
b0 *
bx )
b0 (
0'
0&
b0 %
0$
b0 #
1"
0!
$end
#1000
1,
1&
b10001 %
b10001 *
b10001 6
b1000110010010010100011001001111001000000110010101101101011100000111010001111001001000000110000101100110011101000110010101110010001000000111001001100101011100110110010101110100 3
12
#5000
0"
b1 -
b1 0
1$
#6000
b100010 %
b100010 *
b100010 6
1&
#10000
0$
#15000
b10 -
b10 0
1$
#16000
b110011 %
b110011 *
b110011 6
1&
#20000
0$
#25000
b11 -
b11 0
1$
#26000
1+
0,
1'
b111000001101111011100000010000000110001011100110111010000100000001111010010000000110000011110000011000100110001 5
b10001 4
b1101110011011110111010000100000011001010110110101110000011101000111100100100000011000010110011001110100011001010111001000100000011100000111010101110011011010000110010101110011 3
0&
#30000
0$
#35000
b10 -
b1 /
b10001 #
b10001 .
1$
#36000
b111000001101111011100000010000000110010011011100110010000100000001111010010000000110000011110000011001000110010 5
b100010 4
b111000001101111011100000010000000110001011100110111010000100000001111010010000000110000011110000011000100110001 3
1'
#40000
0$
#45000
b1 -
b10 /
b100010 #
b100010 .
1$
#46000
b111000001101111011100000010000000110011011100100110010000100000001111010010000000110000011110000011001100110011 5
b110011 4
b111000001101111011100000010000000110010011011100110010000100000001111010010000000110000011110000011001000110010 3
1'
#50000
0$
#55000
0+
1"
b0 -
b11 /
b110011 #
b110011 .
1$
#56000
1,
1&
b0 %
b0 *
b0 6
b0 )
b110010101101101011100000111010001111001001000000110000101100110011101000110010101110010001000000110010001110010011000010110100101101110011010010110111001100111 3
0'
#60000
0$
#65000
0"
b1 -
b100 0
1$
#66000
b1 %
b1 *
b1 6
b1 )
1&
#70000
0$
#75000
b10 -
b101 0
1$
#76000
b10 %
b10 *
b10 6
b10 )
1&
#80000
0$
#85000
b11 -
b110 0
1$
#86000
b11 %
b11 *
b11 6
b11 )
1&
#90000
0$
#95000
b100 -
b111 0
1$
#96000
b100 %
b100 *
b100 6
b100 )
1&
#100000
0$
#105000
b101 -
b1000 0
1$
#106000
b101 %
b101 *
b101 6
b101 )
1&
#110000
0$
#115000
b110 -
b1001 0
1$
#116000
b110 %
b110 *
b110 6
b110 )
1&
#120000
0$
#125000
b111 -
b1010 0
1$
#126000
b111 %
b111 *
b111 6
b111 )
1&
#130000
0$
#135000
b1000 -
b1011 0
1$
#136000
b1000 %
b1000 *
b1000 6
b1000 )
1&
#140000
0$
#145000
b1001 -
b1100 0
1$
#146000
b1001 %
b1001 *
b1001 6
b1001 )
1&
#150000
0$
#155000
b1010 -
b1101 0
1$
#156000
b1010 %
b1010 *
b1010 6
b1010 )
1&
#160000
0$
#165000
b1011 -
b1110 0
1$
#166000
b1011 %
b1011 *
b1011 6
b1011 )
1&
#170000
0$
#175000
b1100 -
b1111 0
1$
#176000
b1100 %
b1100 *
b1100 6
b1100 )
1&
#180000
0$
#185000
b1101 -
b10000 0
1$
#186000
b1101 %
b1101 *
b1101 6
b1101 )
1&
#190000
0$
#195000
b1110 -
b10001 0
1$
#196000
b1110 %
b1110 *
b1110 6
b1110 )
1&
#200000
0$
#205000
b1111 -
b10010 0
1$
#206000
b1111 %
b1111 *
b1111 6
b1111 )
1&
#210000
0$
#215000
b10000 -
b10011 0
1$
#216000
b10000 %
b10000 *
b10000 6
b10000 )
1&
#220000
0$
#225000
b10001 -
b10100 0
1$
#226000
b10001 %
b10001 *
b10001 6
b10001 )
1&
#230000
0$
#235000
b10010 -
b10101 0
1$
#236000
b10010 %
b10010 *
b10010 6
b10010 )
1&
#240000
0$
#245000
b10011 -
b10110 0
1$
#246000
b10011 %
b10011 *
b10011 6
b10011 )
1&
#250000
0$
#255000
b10100 -
b10111 0
1$
#256000
b10100 %
b10100 *
b10100 6
b10100 )
1&
#260000
0$
#265000
b10101 -
b11000 0
1$
#266000
b10101 %
b10101 *
b10101 6
b10101 )
1&
#270000
0$
#275000
b10110 -
b11001 0
1$
#276000
b10110 %
b10110 *
b10110 6
b10110 )
1&
#280000
0$
#285000
b10111 -
b11010 0
1$
#286000
b10111 %
b10111 *
b10111 6
b10111 )
1&
#290000
0$
#295000
b11000 -
b11011 0
1$
#296000
b11000 %
b11000 *
b11000 6
b11000 )
1&
#300000
0$
#305000
b11001 -
b11100 0
1$
#306000
b11001 %
b11001 *
b11001 6
b11001 )
1&
#310000
0$
#315000
b11010 -
b11101 0
1$
#316000
b11010 %
b11010 *
b11010 6
b11010 )
1&
#320000
0$
#325000
b11011 -
b11110 0
1$
#326000
b11011 %
b11011 *
b11011 6
b11011 )
1&
#330000
0$
#335000
b11100 -
b11111 0
1$
#336000
b11100 %
b11100 *
b11100 6
b11100 )
1&
#340000
0$
#345000
b11101 -
b100000 0
1$
#346000
b11101 %
b11101 *
b11101 6
b11101 )
1&
#350000
0$
#355000
b11110 -
b100001 0
1$
#356000
b11110 %
b11110 *
b11110 6
b11110 )
1&
#360000
0$
#365000
b11111 -
b100010 0
1$
#366000
b11111 %
b11111 *
b11111 6
b11111 )
1&
#370000
0$
#375000
b100000 -
b100011 0
1$
#376000
b100000 %
b100000 *
b100000 6
b100000 )
1&
#380000
0$
#385000
b100001 -
b100100 0
1$
#386000
b100001 %
b100001 *
b100001 6
b100001 )
1&
#390000
0$
#395000
b100010 -
b100101 0
1$
#396000
b100010 %
b100010 *
b100010 6
b100010 )
1&
#400000
0$
#405000
b100011 -
b100110 0
1$
#406000
b100011 %
b100011 *
b100011 6
b100011 )
1&
#410000
0$
#415000
b100100 -
b100111 0
1$
#416000
b100100 %
b100100 *
b100100 6
b100100 )
1&
#420000
0$
#425000
b100101 -
b101000 0
1$
#426000
b100101 %
b100101 *
b100101 6
b100101 )
1&
#430000
0$
#435000
b100110 -
b101001 0
1$
#436000
b100110 %
b100110 *
b100110 6
b100110 )
1&
#440000
0$
#445000
b100111 -
b101010 0
1$
#446000
b100111 %
b100111 *
b100111 6
b100111 )
1&
#450000
0$
#455000
b101000 -
b101011 0
1$
#456000
b101000 %
b101000 *
b101000 6
b101000 )
1&
#460000
0$
#465000
b101001 -
b101100 0
1$
#466000
b101001 %
b101001 *
b101001 6
b101001 )
1&
#470000
0$
#475000
b101010 -
b101101 0
1$
#476000
b101010 %
b101010 *
b101010 6
b101010 )
1&
#480000
0$
#485000
b101011 -
b101110 0
1$
#486000
b101011 %
b101011 *
b101011 6
b101011 )
1&
#490000
0$
#495000
b101100 -
b101111 0
1$
#496000
b101100 %
b101100 *
b101100 6
b101100 )
1&
#500000
0$
#505000
b101101 -
b110000 0
1$
#506000
b101101 %
b101101 *
b101101 6
b101101 )
1&
#510000
0$
#515000
b101110 -
b110001 0
1$
#516000
b101110 %
b101110 *
b101110 6
b101110 )
1&
#520000
0$
#525000
b101111 -
b110010 0
1$
#526000
b101111 %
b101111 *
b101111 6
b101111 )
1&
#530000
0$
#535000
b110000 -
b110011 0
1$
#536000
b110000 %
b110000 *
b110000 6
b110000 )
1&
#540000
0$
#545000
b110001 -
b110100 0
1$
#546000
b110001 %
b110001 *
b110001 6
b110001 )
1&
#550000
0$
#555000
b110010 -
b110101 0
1$
#556000
b110010 %
b110010 *
b110010 6
b110010 )
1&
#560000
0$
#565000
b110011 -
b110110 0
1$
#566000
b110011 %
b110011 *
b110011 6
b110011 )
1&
#570000
0$
#575000
b110100 -
b110111 0
1$
#576000
b110100 %
b110100 *
b110100 6
b110100 )
1&
#580000
0$
#585000
b110101 -
b111000 0
1$
#586000
b110101 %
b110101 *
b110101 6
b110101 )
1&
#590000
0$
#595000
b110110 -
b111001 0
1$
#596000
b110110 %
b110110 *
b110110 6
b110110 )
1&
#600000
0$
#605000
b110111 -
b111010 0
1$
#606000
b110111 %
b110111 *
b110111 6
b110111 )
1&
#610000
0$
#615000
b111000 -
b111011 0
1$
#616000
b111000 %
b111000 *
b111000 6
b111000 )
1&
#620000
0$
#625000
b111001 -
b111100 0
1$
#626000
b111001 %
b111001 *
b111001 6
b111001 )
1&
#630000
0$
#635000
b111010 -
b111101 0
1$
#636000
b111010 %
b111010 *
b111010 6
b111010 )
1&
#640000
0$
#645000
b111011 -
b111110 0
1$
#646000
b111011 %
b111011 *
b111011 6
b111011 )
1&
#650000
0$
#655000
b111100 -
b111111 0
1$
#656000
b111100 %
b111100 *
b111100 6
b111100 )
1&
#660000
0$
#665000
b111101 -
b1000000 0
1$
#666000
b111101 %
b111101 *
b111101 6
b111101 )
1&
#670000
0$
#675000
b111110 -
b1000001 0
1$
#676000
b111110 %
b111110 *
b111110 6
b111110 )
1&
#680000
0$
#685000
b111111 -
b1000010 0
1$
#686000
b111111 %
b111111 *
b111111 6
b111111 )
1&
#690000
0$
#695000
b1000000 -
b1000011 0
1$
#696000
b1000000 %
b1000000 *
b1000000 6
b1000000 )
1&
#700000
0$
#705000
b1000001 -
b1000100 0
1$
#706000
b1000001 %
b1000001 *
b1000001 6
b1000001 )
1&
#710000
0$
#715000
b1000010 -
b1000101 0
1$
#716000
b1000010 %
b1000010 *
b1000010 6
b1000010 )
1&
#720000
0$
#725000
b1000011 -
b1000110 0
1$
#726000
b1000011 %
b1000011 *
b1000011 6
b1000011 )
1&
#730000
0$
#735000
b1000100 -
b1000111 0
1$
#736000
b1000100 %
b1000100 *
b1000100 6
b1000100 )
1&
#740000
0$
#745000
b1000101 -
b1001000 0
1$
#746000
b1000101 %
b1000101 *
b1000101 6
b1000101 )
1&
#750000
0$
#755000
b1000110 -
b1001001 0
1$
#756000
b1000110 %
b1000110 *
b1000110 6
b1000110 )
1&
#760000
0$
#765000
b1000111 -
b1001010 0
1$
#766000
b1000111 %
b1000111 *
b1000111 6
b1000111 )
1&
#770000
0$
#775000
b1001000 -
b1001011 0
1$
#776000
b1001000 %
b1001000 *
b1001000 6
b1001000 )
1&
#780000
0$
#785000
b1001001 -
b1001100 0
1$
#786000
b1001001 %
b1001001 *
b1001001 6
b1001001 )
1&
#790000
0$
#795000
b1001010 -
b1001101 0
1$
#796000
b1001010 %
b1001010 *
b1001010 6
b1001010 )
1&
#800000
0$
#805000
b1001011 -
b1001110 0
1$
#806000
b1001011 %
b1001011 *
b1001011 6
b1001011 )
1&
#810000
0$
#815000
b1001100 -
b1001111 0
1$
#816000
b1001100 %
b1001100 *
b1001100 6
b1001100 )
1&
#820000
0$
#825000
b1001101 -
b1010000 0
1$
#826000
b1001101 %
b1001101 *
b1001101 6
b1001101 )
1&
#830000
0$
#835000
b1001110 -
b1010001 0
1$
#836000
b1001110 %
b1001110 *
b1001110 6
b1001110 )
1&
#840000
0$
#845000
b1001111 -
b1010010 0
1$
#846000
b1001111 %
b1001111 *
b1001111 6
b1001111 )
1&
#850000
0$
#855000
b1010000 -
b1010011 0
1$
#856000
b1010000 %
b1010000 *
b1010000 6
b1010000 )
1&
#860000
0$
#865000
b1010001 -
b1010100 0
1$
#866000
b1010001 %
b1010001 *
b1010001 6
b1010001 )
1&
#870000
0$
#875000
b1010010 -
b1010101 0
1$
#876000
b1010010 %
b1010010 *
b1010010 6
b1010010 )
1&
#880000
0$
#885000
b1010011 -
b1010110 0
1$
#886000
b1010011 %
b1010011 *
b1010011 6
b1010011 )
1&
#890000
0$
#895000
b1010100 -
b1010111 0
1$
#896000
b1010100 %
b1010100 *
b1010100 6
b1010100 )
1&
#900000
0$
#905000
b1010101 -
b1011000 0
1$
#906000
b1010101 %
b1010101 *
b1010101 6
b1010101 )
1&
#910000
0$
#915000
b1010110 -
b1011001 0
1$
#916000
b1010110 %
b1010110 *
b1010110 6
b1010110 )
1&
#920000
0$
#925000
b1010111 -
b1011010 0
1$
#926000
b1010111 %
b1010111 *
b1010111 6
b1010111 )
1&
#930000
0$
#935000
b1011000 -
b1011011 0
1$
#936000
b1011000 %
b1011000 *
b1011000 6
b1011000 )
1&
#940000
0$
#945000
b1011001 -
b1011100 0
1$
#946000
b1011001 %
b1011001 *
b1011001 6
b1011001 )
1&
#950000
0$
#955000
b1011010 -
b1011101 0
1$
#956000
b1011010 %
b1011010 *
b1011010 6
b1011010 )
1&
#960000
0$
#965000
b1011011 -
b1011110 0
1$
#966000
b1011011 %
b1011011 *
b1011011 6
b1011011 )
1&
#970000
0$
#975000
b1011100 -
b1011111 0
1$
#976000
b1011100 %
b1011100 *
b1011100 6
b1011100 )
1&
#980000
0$
#985000
b1011101 -
b1100000 0
1$
#986000
b1011101 %
b1011101 *
b1011101 6
b1011101 )
1&
#990000
0$
#995000
b1011110 -
b1100001 0
1$
#996000
b1011110 %
b1011110 *
b1011110 6
b1011110 )
1&
#1000000
0$
#1005000
b1011111 -
b1100010 0
1$
#1006000
b1011111 %
b1011111 *
b1011111 6
b1011111 )
1&
#1010000
0$
#1015000
b1100000 -
b1100011 0
1$
#1016000
b1100000 %
b1100000 *
b1100000 6
b1100000 )
1&
#1020000
0$
#1025000
b1100001 -
b1100100 0
1$
#1026000
b1100001 %
b1100001 *
b1100001 6
b1100001 )
1&
#1030000
0$
#1035000
b1100010 -
b1100101 0
1$
#1036000
b1100010 %
b1100010 *
b1100010 6
b1100010 )
1&
#1040000
0$
#1045000
b1100011 -
b1100110 0
1$
#1046000
b1100011 %
b1100011 *
b1100011 6
b1100011 )
1&
#1050000
0$
#1055000
b1100100 -
b1100111 0
1$
#1056000
b1100100 %
b1100100 *
b1100100 6
b1100100 )
1&
#1060000
0$
#1065000
b1100101 -
b1101000 0
1$
#1066000
b1100101 %
b1100101 *
b1100101 6
b1100101 )
1&
#1070000
0$
#1075000
b1100110 -
b1101001 0
1$
#1076000
b1100110 %
b1100110 *
b1100110 6
b1100110 )
1&
#1080000
0$
#1085000
b1100111 -
b1101010 0
1$
#1086000
b1100111 %
b1100111 *
b1100111 6
b1100111 )
1&
#1090000
0$
#1095000
b1101000 -
b1101011 0
1$
#1096000
b1101000 %
b1101000 *
b1101000 6
b1101000 )
1&
#1100000
0$
#1105000
b1101001 -
b1101100 0
1$
#1106000
b1101001 %
b1101001 *
b1101001 6
b1101001 )
1&
#1110000
0$
#1115000
b1101010 -
b1101101 0
1$
#1116000
b1101010 %
b1101010 *
b1101010 6
b1101010 )
1&
#1120000
0$
#1125000
b1101011 -
b1101110 0
1$
#1126000
b1101011 %
b1101011 *
b1101011 6
b1101011 )
1&
#1130000
0$
#1135000
b1101100 -
b1101111 0
1$
#1136000
b1101100 %
b1101100 *
b1101100 6
b1101100 )
1&
#1140000
0$
#1145000
b1101101 -
b1110000 0
1$
#1146000
b1101101 %
b1101101 *
b1101101 6
b1101101 )
1&
#1150000
0$
#1155000
b1101110 -
b1110001 0
1$
#1156000
b1101110 %
b1101110 *
b1101110 6
b1101110 )
1&
#1160000
0$
#1165000
b1101111 -
b1110010 0
1$
#1166000
b1101111 %
b1101111 *
b1101111 6
b1101111 )
1&
#1170000
0$
#1175000
b1110000 -
b1110011 0
1$
#1176000
b1110000 %
b1110000 *
b1110000 6
b1110000 )
1&
#1180000
0$
#1185000
b1110001 -
b1110100 0
1$
#1186000
b1110001 %
b1110001 *
b1110001 6
b1110001 )
1&
#1190000
0$
#1195000
b1110010 -
b1110101 0
1$
#1196000
b1110010 %
b1110010 *
b1110010 6
b1110010 )
1&
#1200000
0$
#1205000
b1110011 -
b1110110 0
1$
#1206000
b1110011 %
b1110011 *
b1110011 6
b1110011 )
1&
#1210000
0$
#1215000
b1110100 -
b1110111 0
1$
#1216000
b1110100 %
b1110100 *
b1110100 6
b1110100 )
1&
#1220000
0$
#1225000
b1110101 -
b1111000 0
1$
#1226000
b1110101 %
b1110101 *
b1110101 6
b1110101 )
1&
#1230000
0$
#1235000
b1110110 -
b1111001 0
1$
#1236000
b1110110 %
b1110110 *
b1110110 6
b1110110 )
1&
#1240000
0$
#1245000
b1110111 -
b1111010 0
1$
#1246000
b1110111 %
b1110111 *
b1110111 6
b1110111 )
1&
#1250000
0$
#1255000
b1111000 -
b1111011 0
1$
#1256000
b1111000 %
b1111000 *
b1111000 6
b1111000 )
1&
#1260000
0$
#1265000
b1111001 -
b1111100 0
1$
#1266000
b1111001 %
b1111001 *
b1111001 6
b1111001 )
1&
#1270000
0$
#1275000
b1111010 -
b1111101 0
1$
#1276000
b1111010 %
b1111010 *
b1111010 6
b1111010 )
1&
#1280000
0$
#1285000
b1111011 -
b1111110 0
1$
#1286000
b1111011 %
b1111011 *
b1111011 6
b1111011 )
1&
#1290000
0$
#1295000
b1111100 -
b1111111 0
1$
#1296000
b1111100 %
b1111100 *
b1111100 6
b1111100 )
1&
#1300000
0$
#1305000
b1111101 -
b0 0
1$
#1306000
b1111101 %
b1111101 *
b1111101 6
b1111101 )
1&
#1310000
0$
#1315000
b1111110 -
b1 0
1$
#1316000
b1111110 %
b1111110 *
b1111110 6
b1111110 )
1&
#1320000
0$
#1325000
b1111111 -
b10 0
1$
#1326000
b1111111 %
b1111111 *
b1111111 6
b1111111 )
1&
#1330000
0$
#1335000
0,
1!
b10000000 -
b11 0
1$
#1336000
b11101110 %
b11101110 *
b11101110 6
b11001100111010101101100011011000010000001100001011001100111010001100101011100100010000000110001001100100011100000100000011100000111010101110011011010000110010101110011 3
b10000000 )
1&
#1340000
0$
#1345000
1$
#1346000
1+
1'
b10101010 %
b10101010 *
b111000001110101011100110110100000100000011010010110011101101110011011110111001001100101011001000010000001110111011010000110100101101100011001010010000001100110011101010110110001101100 3
1&
#1350000
0$
#1355000
1,
0!
b1111111 -
b100 /
b0 #
b0 .
1$
#1356000
0+
0,
b111001101101000011011110111010101101100011001000010000001101110011011110111010000100000011000100110010100100000011001100111010101101100011011000010000001100001011001100111010001100101011100100010000001110011011010010110110101110101011011000111010001100001011011100110010101101111011101010111001100100000011100000111010101110011011010000010101101110000011011110111000000100000011000100110010101100011011000010111010101110011011001010010000001110000011101010111001101101000001000000111011101100001011100110010000001101001011001110110111001101111011100100110010101100100001000000110010001110101011001010010000001110100011011110010000001100110011010010110011001101111001000000110011001110101011011000110110000100000011000010111010000100000011101000110100001100001011101000010000001110100011010010110110101100101001000000110000101101110011001000010000001110000011011110111000001110000011001010110010000100000011100110111010101100011011000110110010101110011011100110110011001110101011011000010000001100010011001010110001101100001011101010111001101100101001000000110100101110100001000000111011101100001011100110010000001101110011011110111010000100000011001010110110101110000011101000111100100100000 3
0'
0&
#1360000
0$
#1365000
1$
#1370000
0$
#1375000
1$
#1376000
1+
1'
b10000001100011011011110110110101100101011100110010000001101111011101010111010000100000011000010110011001110100011001010111001000100000011101000110100001100101001000000110111101101100011001000010000001100101011011100111010001110010011010010110010101110011 5
b1 4
#1380000
0$
#1385000
b1111110 -
b101 /
b1 #
b1 .
1$
#1386000
b111001101100101011100100111011001100101011001000010000001100001011001100111010001100101011100100010000001110011011010010110110101110101011011000111010001100001011011100110010101101111011101010111001100100000011000010110001101100011011001010111001101110011 5
b10 4
b10000001100011011011110110110101100101011100110010000001101111011101010111010000100000011000010110011001110100011001010111001000100000011101000110100001100101001000000110111101101100011001000010000001100101011011100111010001110010011010010110010101110011 3
1'
#1390000
0$
#1395000
b1111101 -
b110 /
b10 #
b10 .
1$
#1396000
b11 )
b111001101100101011100100111011001100101011001000010000001100001011001100111010001100101011100100010000001110011011010010110110101110101011011000111010001100001011011100110010101101111011101010111001100100000011000010110001101100011011001010111001101110011 3
1'
#1400000
0$
#1405000
b1111100 -
b111 /
b11 #
b11 .
1$
#1406000
b100 )
1'
#1410000
0$
#1415000
b1111011 -
b1000 /
b100 #
b100 .
1$
#1416000
b101 )
1'
#1420000
0$
#1425000
b1111010 -
b1001 /
b101 #
b101 .
1$
#1426000
b110 )
1'
#1430000
0$
#1435000
b1111001 -
b1010 /
b110 #
b110 .
1$
#1436000
b111 )
1'
#1440000
0$
#1445000
b1111000 -
b1011 /
b111 #
b111 .
1$
#1446000
b1000 )
1'
#1450000
0$
#1455000
b1110111 -
b1100 /
b1000 #
b1000 .
1$
#1456000
b1001 )
1'
#1460000
0$
#1465000
b1110110 -
b1101 /
b1001 #
b1001 .
1$
#1466000
b1010 )
1'
#1470000
0$
#1475000
b1110101 -
b1110 /
b1010 #
b1010 .
1$
#1476000
b1011 )
1'
#1480000
0$
#1485000
b1110100 -
b1111 /
b1011 #
b1011 .
1$
#1486000
b1100 )
1'
#1490000
0$
#1495000
b1110011 -
b10000 /
b1100 #
b1100 .
1$
#1496000
b1101 )
1'
#1500000
0$
#1505000
b1110010 -
b10001 /
b1101 #
b1101 .
1$
#1506000
b1110 )
1'
#1510000
0$
#1515000
b1110001 -
b10010 /
b1110 #
b1110 .
1$
#1516000
b1111 )
1'
#1520000
0$
#1525000
b1110000 -
b10011 /
b1111 #
b1111 .
1$
#1526000
b10000 )
1'
#1530000
0$
#1535000
b1101111 -
b10100 /
b10000 #
b10000 .
1$
#1536000
b10001 )
1'
#1540000
0$
#1545000
b1101110 -
b10101 /
b10001 #
b10001 .
1$
#1546000
b10010 )
1'
#1550000
0$
#1555000
b1101101 -
b10110 /
b10010 #
b10010 .
1$
#1556000
b10011 )
1'
#1560000
0$
#1565000
b1101100 -
b10111 /
b10011 #
b10011 .
1$
#1566000
b10100 )
1'
#1570000
0$
#1575000
b1101011 -
b11000 /
b10100 #
b10100 .
1$
#1576000
b10101 )
1'
#1580000
0$
#1585000
b1101010 -
b11001 /
b10101 #
b10101 .
1$
#1586000
b10110 )
1'
#1590000
0$
#1595000
b1101001 -
b11010 /
b10110 #
b10110 .
1$
#1596000
b10111 )
1'
#1600000
0$
#1605000
b1101000 -
b11011 /
b10111 #
b10111 .
1$
#1606000
b11000 )
1'
#1610000
0$
#1615000
b1100111 -
b11100 /
b11000 #
b11000 .
1$
#1616000
b11001 )
1'
#1620000
0$
#1625000
b1100110 -
b11101 /
b11001 #
b11001 .
1$
#1626000
b11010 )
1'
#1630000
0$
#1635000
b1100101 -
b11110 /
b11010 #
b11010 .
1$
#1636000
b11011 )
1'
#1640000
0$
#1645000
b1100100 -
b11111 /
b11011 #
b11011 .
1$
#1646000
b11100 )
1'
#1650000
0$
#1655000
b1100011 -
b100000 /
b11100 #
b11100 .
1$
#1656000
b11101 )
1'
#1660000
0$
#1665000
b1100010 -
b100001 /
b11101 #
b11101 .
1$
#1666000
b11110 )
1'
#1670000
0$
#1675000
b1100001 -
b100010 /
b11110 #
b11110 .
1$
#1676000
b11111 )
1'
#1680000
0$
#1685000
b1100000 -
b100011 /
b11111 #
b11111 .
1$
#1686000
b100000 )
1'
#1690000
0$
#1695000
b1011111 -
b100100 /
b100000 #
b100000 .
1$
#1696000
b100001 )
1'
#1700000
0$
#1705000
b1011110 -
b100101 /
b100001 #
b100001 .
1$
#1706000
b100010 )
1'
#1710000
0$
#1715000
b1011101 -
b100110 /
b100010 #
b100010 .
1$
#1716000
b100011 )
1'
#1720000
0$
#1725000
b1011100 -
b100111 /
b100011 #
b100011 .
1$
#1726000
b100100 )
1'
#1730000
0$
#1735000
b1011011 -
b101000 /
b100100 #
b100100 .
1$
#1736000
b100101 )
1'
#1740000
0$
#1745000
b1011010 -
b101001 /
b100101 #
b100101 .
1$
#1746000
b100110 )
1'
#1750000
0$
#1755000
b1011001 -
b101010 /
b100110 #
b100110 .
1$
#1756000
b100111 )
1'
#1760000
0$
#1765000
b1011000 -
b101011 /
b100111 #
b100111 .
1$
#1766000
b101000 )
1'
#1770000
0$
#1775000
b1010111 -
b101100 /
b101000 #
b101000 .
1$
#1776000
b101001 )
1'
#1780000
0$
#1785000
b1010110 -
b101101 /
b101001 #
b101001 .
1$
#1786000
b101010 )
1'
#1790000
0$
#1795000
b1010101 -
b101110 /
b101010 #
b101010 .
1$
#1796000
b101011 )
1'
#1800000
0$
#1805000
b1010100 -
b101111 /
b101011 #
b101011 .
1$
#1806000
b101100 )
1'
#1810000
0$
#1815000
b1010011 -
b110000 /
b101100 #
b101100 .
1$
#1816000
b101101 )
1'
#1820000
0$
#1825000
b1010010 -
b110001 /
b101101 #
b101101 .
1$
#1826000
b101110 )
1'
#1830000
0$
#1835000
b1010001 -
b110010 /
b101110 #
b101110 .
1$
#1836000
b101111 )
1'
#1840000
0$
#1845000
b1010000 -
b110011 /
b101111 #
b101111 .
1$
#1846000
b110000 )
1'
