lab4_9_rtl.v
// ============================================================
// Lab 4-9 (RTL Project) : UART controller interface to a memory
// Objective: Design an interface to a memory block that executes
// memory read/write commands coming from a UART device.
//   * UART serial-to-parallel interface  (uart_rx)
//   * UART parallel-to-serial interface  (uart_tx)
//   * FIFOs buffering UART commands/data in both directions
//   * Parallel interface to the memory block (read/write ops)
//   * 2-port memory model (one read port, one write port)
//
// Command protocol (bytes received over UART):
//   byte0 : 8'h01 = WRITE command, 8'h00 = READ command
//   byte1 : address (8-bit)
//   byte2 : data    (only for WRITE)
// Response: for a READ, one data byte is sent back over UART.
// ============================================================
`timescale 1ns/1ps

// ------------------------------------------------------------
// UART receiver : serial -> parallel (8N1, 16x oversampling)
// ------------------------------------------------------------
module uart_rx(rx_out, rx_valid, rx_serial, clk, reset);
    parameter CLKS_PER_BIT = 16;
    output reg [7:0] rx_out;
    output reg       rx_valid;
    input            rx_serial, clk, reset;

    localparam IDLE  = 2'd0, START = 2'd1, DATA = 2'd2, STOP = 2'd3;
    reg [1:0] state;
    reg [7:0] clk_count;
    reg [2:0] bit_index;
    reg [7:0] rx_data;

    // two-flop synchronizer
    reg r1, r2;
    wire rx_sync = r2;
    always @(posedge clk or posedge reset)
        if (reset) begin r1 <= 1'b1; r2 <= 1'b1; end
        else       begin r1 <= rx_serial; r2 <= r1; end

    always @(posedge clk or posedge reset) begin
        if (reset) begin
            state     <= IDLE;
            clk_count <= 8'd0;
            bit_index <= 3'd0;
            rx_data   <= 8'd0;
            rx_out    <= 8'd0;
            rx_valid  <= 1'b0;
        end else begin
            rx_valid <= 1'b0;
            case (state)
                IDLE:
                    if (rx_sync == 1'b0) begin
                        state     <= START;
                        clk_count <= 8'd0;
                    end
                START:   // verify start bit at its middle
                    if (clk_count == (CLKS_PER_BIT/2)-1) begin
                        if (rx_sync == 1'b0) begin
                            state     <= DATA;
                            clk_count <= 8'd0;
                            bit_index <= 3'd0;
                        end else
                            state <= IDLE;
                    end else
                        clk_count <= clk_count + 8'd1;
                DATA:    // sample each bit in its middle
                  if (clk_count == (CLKS_PER_BIT)-1) begin
                        clk_count          <= 8'd0;
                        rx_data[bit_index] <= rx_sync;
                        if (bit_index == 3'd7)
                            state <= STOP;
                        else
                            bit_index <= bit_index + 3'd1;
                    end else
                        clk_count <= clk_count + 8'd1;
              STOP: if (clk_count == (CLKS_PER_BIT)-1) begin
    						clk_count <= 8'd0;
    						if (rx_sync == 1'b1) begin
       							 rx_out   <= rx_data;
        						rx_valid <= 1'b1;
    						end
    					state <= IDLE;          // always return to IDLE
					end else
    					clk_count <= clk_count + 8'd1;
                default: state <= IDLE;
            endcase
        end
    end
endmodule

// ------------------------------------------------------------
// UART transmitter : parallel -> serial (8N1)
// ------------------------------------------------------------
module uart_tx(tx_serial, tx_busy, tx_in, tx_start, clk, reset);
    parameter CLKS_PER_BIT = 16;
    output reg       tx_serial;
    output reg       tx_busy;
    input      [7:0] tx_in;
    input            tx_start, clk, reset;

    localparam IDLE  = 2'd0, START = 2'd1, DATA = 2'd2, STOP = 2'd3;
    reg [1:0] state;
    reg [7:0] clk_count;
    reg [2:0] bit_index;
    reg [7:0] data;

    always @(posedge clk or posedge reset) begin
        if (reset) begin
            state     <= IDLE;
            clk_count <= 8'd0;
            bit_index <= 3'd0;
            data      <= 8'd0;
            tx_serial <= 1'b1;
            tx_busy   <= 1'b0;
        end else begin
            case (state)
                IDLE: begin
                    tx_serial <= 1'b1;
                    clk_count <= 8'd0;
                    bit_index <= 3'd0;
                    if (tx_start) begin
                        tx_busy <= 1'b1;
                        data    <= tx_in;
                        state   <= START;
                    end else
                        tx_busy <= 1'b0;
                end
                START: begin
                    tx_busy   <= 1'b1;
                    tx_serial <= 1'b0;               // start bit
                    if (clk_count == CLKS_PER_BIT-1) begin
                        clk_count <= 8'd0;
                        state     <= DATA;
                    end else
                        clk_count <= clk_count + 8'd1;
                end
                DATA: begin
                    tx_busy   <= 1'b1;
                    tx_serial <= data[bit_index];    // LSB first
                    if (clk_count == CLKS_PER_BIT-1) begin
                        clk_count <= 8'd0;
                        if (bit_index == 3'd7)
                            state <= STOP;
                        else
                            bit_index <= bit_index + 3'd1;
                    end else
                        clk_count <= clk_count + 8'd1;
                end
                STOP: begin
                    tx_busy   <= 1'b1;
                    tx_serial <= 1'b1;               // stop bit
                    if (clk_count == CLKS_PER_BIT-1) begin
                        clk_count <= 8'd0;
                        state     <= IDLE;
                    end else
                        clk_count <= clk_count + 8'd1;
                end
                default: state <= IDLE;
            endcase
        end
    end
endmodule

// ------------------------------------------------------------
// FIFO : 128 entries x 8 bits (from Lab 4-8)
// ------------------------------------------------------------
module fifo(d_in, d_in_valid, d_out, d_out_req, clk, reset, full, empty);
    input  [7:0] d_in;
    input        d_in_valid, d_out_req, clk, reset;
    output reg [7:0] d_out;
    output       full, empty;

    reg [7:0] mem [0:127];
    reg [6:0] wr_ptr, rd_ptr;
    reg [7:0] count;

    integer i;
    assign full  = (count == 8'd128);
    assign empty = (count == 8'd0);

    wire do_push = d_in_valid & ~full;
    wire do_pop  = d_out_req  & ~empty;

    always @(posedge clk or posedge reset) begin
        if(reset) begin
            wr_ptr <= 7'd0; 
            rd_ptr <= 7'd0; 
            count <= 8'd0; 
            d_out <= 8'd0;
          for (int i = 0; i < 128; i = i + 1)
                mem[i] <= 8'b0;
        end
        else begin
        if (do_push) begin
            mem[wr_ptr] <= d_in;
            wr_ptr      <= wr_ptr + 7'd1;
        end
        if (do_pop) begin
            d_out  <= mem[rd_ptr];
            rd_ptr <= rd_ptr + 7'd1;
        end
        case ({do_push, do_pop})
            2'b10:   count <= count + 8'd1;
            2'b01:   count <= count - 8'd1;
            default: count <= count;
        endcase
        end
    end
endmodule

// ------------------------------------------------------------
// 2-port memory : one write port + one read port (asynchronous read)
// ------------------------------------------------------------
module ram_2port(d_out, d_in, wr_addr, rd_addr, we, clk, reset);
    output [7:0] d_out;
    input  [7:0] d_in;
    input  [7:0] wr_addr, rd_addr;
    input        we, clk, reset;

    reg [7:0] mem [0:255];

    assign d_out = mem[rd_addr];          // read port

    always @(posedge clk or posedge reset)                 // write port
    begin
        if(reset)
            for (int i = 0; i < 256; i = i + 1)
                mem[i] <= 8'b0;
        else if (we)
            mem[wr_addr] <= d_in;
    end
endmodule

// ------------------------------------------------------------
// Top level : UART -> command FIFO -> controller -> RAM / TX FIFO -> UART
// ------------------------------------------------------------
module uart_mem_top(tx_serial, rx_serial, clk, reset);
    parameter CLKS_PER_BIT = 16;
    input  rx_serial, clk, reset;
    output tx_serial;

    // UART RX -> command byte stream
    wire tx_busy;
    wire [7:0] rx_byte;
    wire       rx_valid;
    uart_rx #(CLKS_PER_BIT) u_rx (
        .rx_out(rx_byte), .rx_valid(rx_valid),
        .rx_serial(rx_serial), .clk(clk), .reset(reset));

    // command	 FIFO (buffers UART commands)
    wire [7:0] cmd_dout;
    wire       cmd_full, cmd_empty;
    wire       cmd_pop;
    fifo u_cmd_fifo (
        .d_in(rx_byte), .d_in_valid(rx_valid), .d_out(cmd_dout),
        .d_out_req(cmd_pop), .clk(clk), .reset(reset), .full(cmd_full), .empty(cmd_empty));

    // controller FSM
    localparam IDLE    = 3'd0,
               CMD     = 3'd1,
               WR_ADDR = 3'd2,
               WR_DATA = 3'd3,
               RD_ADDR = 3'd4,
               RD_EXEC = 3'd5;
    reg [2:0] state;
    reg [7:0] addr_reg;

    //assign cmd_pop = !cmd_empty &&
                     //((state == IDLE) || (state == CMD) || (state == WR_ADDR));
  //assign cmd_pop = !cmd_empty && (state == WR_DATA);
  assign cmd_pop = !cmd_empty && ((state == CMD)     ||   // pop command byte
                                (state == WR_ADDR)  ||   // pop address
                                  (state == IDLE));     

    always @(posedge clk or posedge reset) begin
        if (reset)
            state <= IDLE;
        else begin
            case (state)
                IDLE:    if (!cmd_empty) state <= CMD;
              	CMD:     if (!cmd_empty) state <= (cmd_dout == 8'h01) ? WR_ADDR : RD_ADDR;
              	WR_ADDR: if (!cmd_empty) begin addr_reg <= cmd_dout; state <= WR_DATA; end
                WR_DATA: state <= IDLE;      // memory write happens this cycle
                RD_ADDR: begin addr_reg <= cmd_dout; state <= RD_EXEC; end
                RD_EXEC: state <= IDLE;      // read data pushed to TX FIFO
                default: state <= IDLE;
            endcase
        end
    end

    // memory (write port driven by controller, read port combinational)
    wire [7:0] mem_dout;
    wire       mem_we = (state == WR_DATA);
    ram_2port u_ram (
        .d_out(mem_dout), .d_in(cmd_dout),
        .wr_addr(addr_reg), .rd_addr(addr_reg),
        .we(mem_we), .clk(clk), .reset(reset));

    // TX FIFO (buffers responses back to the UART)
    wire [7:0] tx_dout;
    wire       tx_full, tx_empty;
    reg        tx_pop, tx_start;
    fifo u_tx_fifo (
        .d_in(mem_dout), .d_in_valid(state == RD_EXEC), .d_out(tx_dout),
        .d_out_req(tx_pop), .clk(clk), .reset(reset), .full(tx_full), .empty(tx_empty));

    // start a TX transmission whenever the UART is idle and data is waiting
    always @(posedge clk or posedge reset) begin
        if (reset) begin
            tx_pop   <= 1'b0;
            tx_start <= 1'b0;
        end else begin
            tx_pop   <= 1'b0;                    // default: pulse for 1 cycle
            tx_start <= tx_pop & ~tx_busy;       // d_out valid by now
            if (!tx_busy && !tx_empty && !tx_pop && !tx_start)
                tx_pop <= 1'b1;                  // load d_out with the head byte
        end
    end

    
    uart_tx #(CLKS_PER_BIT) u_tx (
        .tx_serial(tx_serial), .tx_busy(tx_busy), .tx_in(tx_dout),
        .tx_start(tx_start), .clk(clk), .reset(reset));
endmodule

lab4_9_tb.v
// ============================================================
// Lab 4-9 : Testbench
// Sends UART commands: write 0x5A to addr 0x10, write 0xC3 to
// addr 0x11, then reads both locations back over the UART TX
// line and checks the returned data.
// ============================================================
`timescale 1ns/1ps
module lab4_9_tb;
    parameter CLKS_PER_BIT = 16;
    localparam BIT = CLKS_PER_BIT * 10;   // 160 ns per UART bit

    reg clk = 0;
    always #5 clk = ~clk;

    integer errors = 0;

    reg  reset, rx_serial;
    wire tx_serial;
    uart_mem_top #(CLKS_PER_BIT) dut (
        .tx_serial(tx_serial), .rx_serial(rx_serial), .clk(clk), .reset(reset));

    task check;
        input condition;
        input [255:0] msg;
        begin
            if (!condition) begin
                errors = errors + 1;
                $display("FAIL: %0s (time=%0t)", msg, $time);
            end
        end
    endtask

    // host-side UART transmit: 8N1, LSB first
    task send_byte;
        input [7:0] b;
        integer k;
        begin
            $display("Inside task send_byte at time =%0t)", $time);
            rx_serial = 1'b0;            // start bit
            #(BIT);
            for (k = 0; k < 8; k = k + 1) begin
                rx_serial = b[k];
                $display("rx_serial = b[k] -> b = %0h, k = %0h, rx_serial = %0h at time =%0t)", b, k, rx_serial, $time);
                #(BIT);
            end
            rx_serial = 1'b1;            // stop bit
            #(BIT);
        end
    endtask

    // host-side UART receive
    task recv_byte;
        output [7:0] b;
        integer k;
        begin
            $display("Inside task recv_byte at time =%0t)", $time);
            @(negedge tx_serial);        // wait for start bit
            #(BIT/2);                    // middle of start bit
            for (k = 0; k < 8; k = k + 1) begin
                #(BIT);
                b[k] = tx_serial;
                $display("b[k] = tx_serial -> b = %0h, k = %0h, tx_serial = %0h at time =%0t)", b, k, tx_serial, $time);
            end
            #(BIT);                      // pass stop bit
        end
    endtask

    reg [7:0] got;

    initial begin
        reset = 1; rx_serial = 1'b1; got = 8'b0;
        repeat (5) @(posedge clk);
        reset = 0;
        @(posedge clk);

        // ---- WRITE 0x5A -> address 0x10 ----
        send_byte(8'h01);                // WRITE command
        send_byte(8'h10);                // address
        send_byte(8'h5A);                // data
      repeat (20) @(posedge clk);

        // ---- WRITE 0xC3 -> address 0x11 ----
        send_byte(8'h01);
        send_byte(8'h11);
        send_byte(8'hC3);
        repeat (20) @(posedge clk);
		$display("mem[0x10] = %h, mem[0x11] = %h",
         dut.u_ram.mem[8'h10], dut.u_ram.mem[8'h11]);
        // ---- READ address 0x10, expect 0x5A back ----
        $display("---- READ address 0x10, expect 0x5A back ----");
        $display("READ starts at time =%0t)", $time);
        send_byte(8'h00);                // READ command
      $display("READ command =%h", 8'h00);
        send_byte(8'h10);                // address
      $display("READ address =%h and time = %0t", 8'h10, $time);
        recv_byte(got);
      $display("READ received =%h", got);
        check(got === 8'h5A, "read back 0x5A from address 0x10");

        // ---- READ address 0x11, expect 0xC3 back ----
        $display("---- READ address 0x10, expect 0xC3 back ----");
        $display("READ starts at time =%0t)", $time);
        send_byte(8'h00);
      $display("READ command =%h", 8'h00);
        send_byte(8'h11);
      $display("READ address =%h and time = %0t", 8'h11, $time);
        recv_byte(got);
      $display("READ received =%h", got);
        check(got === 8'hC3, "read back 0xC3 from address 0x11");

        // ---- READ back-to-back ----
        $display("---- READ back-to-back ----");
        $display("READ starts at time =%0t)", $time);
      send_byte(8'h00); $display("READ command =%h", 8'h00); send_byte(8'h10); $display("READ address =%h and time = %0t", 8'h10, $time);
      recv_byte(got);
      check(got === 8'h5A, "back-to-back read 0x10 = 0x5A");
      $display("READ received =%h", got);
      send_byte(8'h00); $display("READ command =%h", 8'h00); send_byte(8'h11); $display("READ address =%h and time = %0t", 8'h11, $time);
      recv_byte(got);
      $display("READ received =%h", got);
        check(got === 8'hC3, "back-to-back read 0x11 = 0xC3");
        
        if (errors == 0) $display("LAB 4-9 PASSED");
        else             $display("LAB 4-9 FAILED (%0d errors)", errors);
        $finish;
    end

    // watchdog
    initial begin
        #5_000_000;
        $display("LAB 4-9 FAILED: timeout");
        $finish;
    end
  initial begin
	$dumpfile("dump.vcd"); // waveform file name
	$dumpvars; 
  end
endmodule

dump.vcd
$date
	Sun Sep 20 22:41:23 2026
$end
$version
	Icarus Verilog
$end
$timescale
	1ps
$end
$scope module lab4_9_tb $end
$var wire 1 ! tx_serial $end
$var parameter 64 " BIT $end
$var parameter 32 # CLKS_PER_BIT $end
$var reg 1 $ clk $end
$var reg 8 % got [7:0] $end
$var reg 1 & reset $end
$var reg 1 ' rx_serial $end
$var integer 32 ( errors [31:0] $end
$scope module dut $end
$var wire 1 $ clk $end
$var wire 1 ) cmd_pop $end
$var wire 1 & reset $end
$var wire 1 ' rx_serial $end
$var wire 1 ! tx_serial $end
$var wire 1 * tx_full $end
$var wire 1 + tx_empty $end
$var wire 8 , tx_dout [7:0] $end
$var wire 1 - tx_busy $end
$var wire 1 . rx_valid $end
$var wire 8 / rx_byte [7:0] $end
$var wire 1 0 mem_we $end
$var wire 8 1 mem_dout [7:0] $end
$var wire 1 2 cmd_full $end
$var wire 1 3 cmd_empty $end
$var wire 8 4 cmd_dout [7:0] $end
$var parameter 32 5 CLKS_PER_BIT $end
$var parameter 3 6 CMD $end
$var parameter 3 7 IDLE $end
$var parameter 3 8 RD_ADDR $end
$var parameter 3 9 RD_EXEC $end
$var parameter 3 : WR_ADDR $end
$var parameter 3 ; WR_DATA $end
$var reg 8 < addr_reg [7:0] $end
$var reg 3 = state [2:0] $end
$var reg 1 > tx_pop $end
$var reg 1 ? tx_start $end
$scope module u_cmd_fifo $end
$var wire 1 $ clk $end
$var wire 1 ) d_out_req $end
$var wire 1 @ do_pop $end
$var wire 1 A do_push $end
$var wire 1 & reset $end
$var wire 1 2 full $end
$var wire 1 3 empty $end
$var wire 1 . d_in_valid $end
$var wire 8 B d_in [7:0] $end
$var reg 8 C count [7:0] $end
$var reg 8 D d_out [7:0] $end
$var reg 7 E rd_ptr [6:0] $end
$var reg 7 F wr_ptr [6:0] $end
$scope begin $ivl_for_loop0 $end
$var integer 32 G i [31:0] $end
$upscope $end
$upscope $end
$scope module u_ram $end
$var wire 1 $ clk $end
$var wire 8 H d_in [7:0] $end
$var wire 8 I d_out [7:0] $end
$var wire 8 J rd_addr [7:0] $end
$var wire 1 & reset $end
$var wire 1 0 we $end
$var wire 8 K wr_addr [7:0] $end
$scope begin $ivl_for_loop1 $end
$var integer 32 L i [31:0] $end
$upscope $end
$upscope $end
$scope module u_rx $end
$var wire 1 $ clk $end
$var wire 1 & reset $end
$var wire 1 ' rx_serial $end
$var wire 1 M rx_sync $end
$var parameter 32 N CLKS_PER_BIT $end
$var parameter 2 O DATA $end
$var parameter 2 P IDLE $end
$var parameter 2 Q START $end
$var parameter 2 R STOP $end
$var reg 3 S bit_index [2:0] $end
$var reg 8 T clk_count [7:0] $end
$var reg 1 U r1 $end
$var reg 1 V r2 $end
$var reg 8 W rx_data [7:0] $end
$var reg 8 X rx_out [7:0] $end
$var reg 1 . rx_valid $end
$var reg 2 Y state [1:0] $end
$upscope $end
$scope module u_tx $end
$var wire 1 $ clk $end
$var wire 1 & reset $end
$var wire 1 ? tx_start $end
$var wire 8 Z tx_in [7:0] $end
$var parameter 32 [ CLKS_PER_BIT $end
$var parameter 2 \ DATA $end
$var parameter 2 ] IDLE $end
$var parameter 2 ^ START $end
$var parameter 2 _ STOP $end
$var reg 3 ` bit_index [2:0] $end
$var reg 8 a clk_count [7:0] $end
$var reg 8 b data [7:0] $end
$var reg 2 c state [1:0] $end
$var reg 1 - tx_busy $end
$var reg 1 ! tx_serial $end
$upscope $end
$scope module u_tx_fifo $end
$var wire 1 $ clk $end
$var wire 8 d d_in [7:0] $end
$var wire 1 e d_in_valid $end
$var wire 1 > d_out_req $end
$var wire 1 f do_pop $end
$var wire 1 g do_push $end
$var wire 1 & reset $end
$var wire 1 * full $end
$var wire 1 + empty $end
$var reg 8 h count [7:0] $end
$var reg 8 i d_out [7:0] $end
$var reg 7 j rd_ptr [6:0] $end
$var reg 7 k wr_ptr [6:0] $end
$scope begin $ivl_for_loop0 $end
$var integer 32 l i [31:0] $end
$upscope $end
$upscope $end
$upscope $end
$scope task check $end
$var reg 1 m condition $end
$var reg 256 n msg [255:0] $end
$upscope $end
$scope task recv_byte $end
$var reg 8 o b [7:0] $end
$var integer 32 p k [31:0] $end
$upscope $end
$scope task send_byte $end
$var reg 8 q b [7:0] $end
$var integer 32 r k [31:0] $end
$upscope $end
$upscope $end
$enddefinitions $end
$comment Show the parameter values. $end
$dumpall
b11 _
b1 ^
b0 ]
b10 \
b10000 [
b11 R
b1 Q
b0 P
b10 O
b10000 N
b11 ;
b10 :
b101 9
b100 8
b0 7
b1 6
b10000 5
b10000 #
b10100000 "
$end
#0
$dumpvars
bx r
bx q
bx p
bx o
bx n
xm
b10000000 l
b0 k
b0 j
b0 i
b0 h
0g
0f
0e
bx d
b0 c
b0 b
b0 a
b0 `
b0 Z
b0 Y
b0 X
b0 W
1V
1U
b0 T
b0 S
1M
b100000000 L
bx K
bx J
bx I
b0 H
b10000000 G
b0 F
b0 E
b0 D
b0 C
b0 B
0A
0@
0?
0>
b0 =
bx <
b0 4
13
02
bx 1
00
b0 /
0.
0-
b0 ,
1+
0*
0)
b0 (
1'
1&
b0 %
0$
1!
$end
#5000
b10000000 l
b100000000 L
b10000000 G
1$
#10000
0$
#15000
b10000000 l
b100000000 L
b10000000 G
1$
#20000
0$
#25000
b10000000 l
b100000000 L
b10000000 G
1$
#30000
0$
#35000
b10000000 l
b100000000 L
b10000000 G
1$
#40000
0$
#45000
0&
1$
#50000
0$
#55000
0U
0'
b1 q
1$
#60000
0$
#65000
0M
0V
1$
#70000
0$
#75000
b1 Y
1$
#80000
0$
#85000
b1 T
1$
#90000
0$
#95000
b10 T
1$
#100000
0$
#105000
b11 T
1$
#110000
0$
#115000
b100 T
1$
#120000
0$
#125000
b101 T
1$
#130000
0$
#135000
b110 T
1$
#140000
0$
#145000
b111 T
1$
#150000
0$
#155000
b0 T
b10 Y
1$
#160000
0$
#165000
b1 T
1$
#170000
0$
#175000
b10 T
1$
#180000
0$
#185000
b11 T
1$
#190000
0$
#195000
b100 T
1$
#200000
0$
#205000
b101 T
1$
#210000
0$
#215000
1U
b110 T
1$
1'
b0 r
#220000
0$
#225000
b111 T
1M
1V
1$
#230000
0$
#235000
b1000 T
1$
#240000
0$
#245000
b1001 T
1$
#250000
0$
#255000
b1010 T
1$
#260000
0$
#265000
b1011 T
1$
#270000
0$
#275000
b1100 T
1$
#280000
0$
#285000
b1101 T
1$
#290000
0$
#295000
b1110 T
1$
#300000
0$
#305000
b1111 T
1$
#310000
0$
#315000
b1 S
b1 W
b0 T
1$
#320000
0$
#325000
b1 T
1$
#330000
0$
#335000
b10 T
1$
#340000
0$
#345000
b11 T
1$
#350000
0$
#355000
b100 T
1$
#360000
0$
#365000
b101 T
1$
#370000
0$
#375000
0U
b110 T
1$
0'
b1 r
#380000
0$
#385000
b111 T
0M
0V
1$
#390000
0$
#395000
b1000 T
1$
#400000
0$
#405000
b1001 T
1$
#410000
0$
#415000
b1010 T
1$
#420000
0$
#425000
b1011 T
1$
#430000
0$
#435000
b1100 T
1$
#440000
0$
#445000
b1101 T
1$
#450000
0$
#455000
b1110 T
1$
#460000
0$
#465000
b1111 T
1$
#470000
0$
#475000
b10 S
b0 T
1$
#480000
0$
#485000
b1 T
1$
#490000
0$
#495000
b10 T
1$
#500000
0$
#505000
b11 T
1$
#510000
0$
#515000
b100 T
1$
#520000
0$
#525000
b101 T
1$
#530000
0$
#535000
b110 T
1$
b10 r
#540000
0$
#545000
b111 T
1$
#550000
0$
#555000
b1000 T
1$
#560000
0$
#565000
b1001 T
1$
#570000
0$
#575000
b1010 T
1$
#580000
0$
#585000
b1011 T
1$
#590000
0$
#595000
b1100 T
1$
#600000
0$
#605000
b1101 T
1$
#610000
0$
#615000
b1110 T
1$
#620000
0$
#625000
b1111 T
1$
#630000
0$
#635000
b11 S
b0 T
1$
#640000
0$
#645000
b1 T
1$
#650000
0$
#655000
b10 T
1$
#660000
0$
#665000
b11 T
1$
#670000
0$
#675000
b100 T
1$
#680000
0$
#685000
b101 T
1$
#690000
0$
#695000
b110 T
1$
b11 r
#700000
0$
#705000
b111 T
1$
#710000
0$
#715000
b1000 T
1$
#720000
0$
#725000
b1001 T
1$
#730000
0$
#735000
b1010 T
1$
#740000
0$
#745000
b1011 T
1$
#750000
0$
#755000
b1100 T
1$
#760000
0$
#765000
b1101 T
1$
#770000
0$
#775000
b1110 T
1$
#780000
0$
#785000
b1111 T
1$
#790000
0$
#795000
b100 S
b0 T
1$
#800000
0$
#805000
b1 T
1$
#810000
0$
#815000
b10 T
1$
#820000
0$
#825000
b11 T
1$
#830000
0$
#835000
b100 T
1$
#840000
0$
#845000
b101 T
1$
#850000
0$
#855000
b110 T
1$
b100 r
#860000
0$
#865000
b111 T
1$
#870000
0$
#875000
b1000 T
1$
#880000
0$
#885000
b1001 T
1$
#890000
0$
#895000
b1010 T
1$
#900000
0$
#905000
b1011 T
1$
#910000
0$
#915000
b1100 T
1$
#920000
0$
#925000
b1101 T
1$
#930000
0$
#935000
b1110 T
1$
#940000
0$
#945000
b1111 T
1$
#950000
0$
#955000
b101 S
b0 T
1$
#960000
0$
#965000
b1 T
1$
#970000
0$
#975000
b10 T
1$
#980000
0$
#985000
b11 T
1$
#990000
0$
#995000
b100 T
1$
#1000000
0$
#1005000
b101 T
1$
#1010000
0$
#1015000
b110 T
1$
b101 r
#1020000
0$
#1025000
b111 T
1$
#1030000
0$
#1035000
b1000 T
1$
#1040000
0$
#1045000
b1001 T
1$
#1050000
0$
#1055000
b1010 T
1$
#1060000
0$
#1065000
b1011 T
1$
#1070000
0$
#1075000
b1100 T
1$
#1080000
0$
#1085000
b1101 T
1$
#1090000
0$
#1095000
b1110 T
1$
#1100000
0$
#1105000
b1111 T
1$
#1110000
0$
#1115000
b110 S
b0 T
1$
#1120000
0$
#1125000
b1 T
1$
#1130000
0$
#1135000
b10 T
1$
#1140000
0$
#1145000
b11 T
1$
#1150000
0$
#1155000
b100 T
1$
#1160000
0$
#1165000
b101 T
1$
#1170000
0$
#1175000
b110 T
1$
b110 r
#1180000
0$
#1185000
b111 T
1$
#1190000
0$
#1195000
b1000 T
1$
#1200000
0$
#1205000
b1001 T
1$
#1210000
0$
#1215000
b1010 T
1$
#1220000
0$
#1225000
b1011 T
1$
#1230000
0$
#1235000
b1100 T
1$
#1240000
0$
#1245000
b1101 T
1$
#1250000
0$
#1255000
b1110 T
1$
#1260000
0$
#1265000
b1111 T
1$
#1270000
0$
#1275000
b111 S
b0 T
1$
#1280000
0$
#1285000
b1 T
1$
#1290000
0$
#1295000
b10 T
1$
#1300000
0$
#1305000
b11 T
1$
#1310000
0$
#1315000
b100 T
1$
#1320000
0$
#1325000
b101 T
1$
#1330000
0$
#1335000
b110 T
1$
b111 r
#1340000
0$
#1345000
b111 T
1$
#1350000
0$
#1355000
b1000 T
1$
#1360000
0$
#1365000
b1001 T
1$
#1370000
0$
#1375000
b1010 T
1$
#1380000
0$
#1385000
b1011 T
1$
#1390000
0$
#1395000
b1100 T
1$
#1400000
0$
#1405000
b1101 T
1$
#1410000
0$
#1415000
b1110 T
1$
#1420000
0$
#1425000
b1111 T
1$
#1430000
0$
#1435000
b11 Y
b0 T
1$
#1440000
0$
#1445000
b1 T
1$
#1450000
0$
#1455000
b10 T
1$
#1460000
0$
#1465000
b11 T
1$
#1470000
0$
#1475000
b100 T
1$
#1480000
0$
#1485000
b101 T
1$
#1490000
0$
#1495000
1U
b110 T
1$
1'
b1000 r
#1500000
0$
#1505000
b111 T
1M
1V
1$
#1510000
0$
#1515000
b1000 T
1$
#1520000
0$
#1525000
b1001 T
1$
#1530000
0$
#1535000
b1010 T
1$
#1540000
0$
#1545000
b1011 T
1$
#1550000
0$
#1555000
b1100 T
1$
#1560000
0$
#1565000
b1101 T
1$
#1570000
0$
#1575000
b1110 T
1$
#1580000
0$
#1585000
b1111 T
1$
#1590000
0$
#1595000
1A
b0 Y
1.
b1 /
b1 B
b1 X
b0 T
1$
#1600000
0$
#1605000
1@
0A
1)
0.
03
b1 C
b1 F
1$
#1610000
0$
#1615000
0@
0)
13
b0 C
b1 E
b1 4
b1 D
b1 H
b1 =
1$
#1620000
0$
#1625000
1$
#1630000
0$
#1635000
1$
#1640000
0$
#1645000
1$
#1650000
0$
#1655000
0U
1$
0'
b10000 q
#1660000
0$
#1665000
0M
0V
1$
#1670000
0$
#1675000
b1 Y
1$
#1680000
0$
#1685000
b1 T
1$
#1690000
0$
#1695000
b10 T
1$
#1700000
0$
#1705000
b11 T
1$
#1710000
0$
#1715000
b100 T
1$
#1720000
0$
#1725000
b101 T
1$
#1730000
0$
#1735000
b110 T
1$
#1740000
0$
#1745000
b111 T
1$
#1750000
0$
#1755000
b0 S
b0 T
b10 Y
1$
#1760000
0$
#1765000
b1 T
1$
#1770000
0$
#1775000
b10 T
1$
#1780000
0$
#1785000
b11 T
1$
#1790000
0$
#1795000
b100 T
1$
#1800000
0$
#1805000
b101 T
1$
#1810000
0$
#1815000
b110 T
1$
b0 r
#1820000
0$
#1825000
b111 T
1$
#1830000
0$
#1835000
b1000 T
1$
#1840000
0$
#1845000
b1001 T
1$
#1850000
0$
#1855000
b1010 T
1$
#1860000
0$
#1865000
b1011 T
1$
#1870000
0$
#1875000
b1100 T
1$
#1880000
0$
#1885000
b1101 T
1$
#1890000
0$
#1895000
b1110 T
1$
#1900000
0$
#1905000
b1111 T
1$
#1910000
0$
#1915000
b1 S
b0 W
b0 T
1$
#1920000
0$
#1925000
b1 T
1$
#1930000
0$
#1935000
b10 T
1$
#1940000
0$
#1945000
b11 T
1$
#1950000
0$
#1955000
b100 T
1$
#1960000
0$
#1965000
b101 T
1$
#1970000
0$
#1975000
b110 T
1$
b1 r
#1980000
0$
#1985000
b111 T
1$
#1990000
0$
#1995000
b1000 T
1$
#2000000
0$
#2005000
b1001 T
1$
#2010000
0$
#2015000
b1010 T
1$
#2020000
0$
#2025000
b1011 T
1$
#2030000
0$
#2035000
b1100 T
1$
#2040000
0$
#2045000
b1101 T
1$
#2050000
0$
#2055000
b1110 T
1$
#2060000
0$
#2065000
b1111 T
1$
#2070000
0$
#2075000
b10 S
b0 T
1$
#2080000
0$
#2085000
b1 T
1$
#2090000
0$
#2095000
b10 T
1$
#2100000
0$
#2105000
b11 T
1$
#2110000
0$
#2115000
b100 T
1$
#2120000
0$
#2125000
b101 T
1$
#2130000
0$
#2135000
b110 T
1$
b10 r
#2140000
0$
#2145000
b111 T
1$
#2150000
0$
#2155000
b1000 T
1$
#2160000
0$
#2165000
b1001 T
1$
#2170000
0$
#2175000
b1010 T
1$
#2180000
0$
#2185000
b1011 T
1$
#2190000
0$
#2195000
b1100 T
1$
#2200000
0$
#2205000
b1101 T
1$
#2210000
0$
#2215000
b1110 T
1$
#2220000
0$
#2225000
b1111 T
1$
#2230000
0$
#2235000
b11 S
b0 T
1$
#2240000
0$
#2245000
b1 T
1$
#2250000
0$
#2255000
b10 T
1$
#2260000
0$
#2265000
b11 T
1$
#2270000
0$
#2275000
b100 T
1$
#2280000
0$
#2285000
b101 T
1$
#2290000
0$
#2295000
b110 T
1$
b11 r
#2300000
0$
#2305000
b111 T
1$
#2310000
0$
#2315000
b1000 T
1$
#2320000
0$
#2325000
b1001 T
1$
#2330000
0$
#2335000
b1010 T
1$
#2340000
0$
#2345000
b1011 T
1$
#2350000
0$
#2355000
b1100 T
1$
#2360000
0$
#2365000
b1101 T
1$
#2370000
0$
#2375000
b1110 T
1$
#2380000
0$
#2385000
b1111 T
1$
#2390000
0$
#2395000
b100 S
b0 T
1$
#2400000
0$
#2405000
b1 T
1$
#2410000
0$
#2415000
b10 T
1$
#2420000
0$
#2425000
b11 T
1$
#2430000
0$
#2435000
b100 T
1$
#2440000
0$
#2445000
b101 T
1$
#2450000
0$
#2455000
1U
b110 T
1$
1'
b100 r
#2460000
0$
#2465000
b111 T
1M
1V
1$
#2470000
0$
#2475000
b1000 T
1$
#2480000
0$
#2485000
b1001 T
1$
#2490000
0$
#2495000
b1010 T
1$
#2500000
0$
#2505000
b1011 T
1$
#2510000
0$
